odoo9_addon_customer_outstanding_statement-9.0.1.1.0.99.dev2-py2.7-nspkg.pth
odoo9_addon_customer_outstanding_statement-9.0.1.1.0.99.dev2.dist-info/DESCRIPTION.rst
odoo9_addon_customer_outstanding_statement-9.0.1.1.0.99.dev2.dist-info/METADATA
odoo9_addon_customer_outstanding_statement-9.0.1.1.0.99.dev2.dist-info/RECORD
odoo9_addon_customer_outstanding_statement-9.0.1.1.0.99.dev2.dist-info/WHEEL
odoo9_addon_customer_outstanding_statement-9.0.1.1.0.99.dev2.dist-info/metadata.json
odoo9_addon_customer_outstanding_statement-9.0.1.1.0.99.dev2.dist-info/namespace_packages.txt
odoo9_addon_customer_outstanding_statement-9.0.1.1.0.99.dev2.dist-info/top_level.txt
odoo_addons/customer_outstanding_statement/README.rst
odoo_addons/customer_outstanding_statement/__init__.py
odoo_addons/customer_outstanding_statement/__openerp__.py
odoo_addons/customer_outstanding_statement/i18n/ca.po
odoo_addons/customer_outstanding_statement/i18n/customer_outstanding_statement.pot
odoo_addons/customer_outstanding_statement/i18n/de.po
odoo_addons/customer_outstanding_statement/i18n/es.po
odoo_addons/customer_outstanding_statement/i18n/fr.po
odoo_addons/customer_outstanding_statement/i18n/pt.po
odoo_addons/customer_outstanding_statement/report/__init__.py
odoo_addons/customer_outstanding_statement/report/customer_outstanding_statement.py
odoo_addons/customer_outstanding_statement/static/description/Outstanding_Statement.png
odoo_addons/customer_outstanding_statement/static/description/icon.png
odoo_addons/customer_outstanding_statement/static/description/index.html
odoo_addons/customer_outstanding_statement/tests/__init__.py
odoo_addons/customer_outstanding_statement/tests/test_customer_outstanding_statement.py
odoo_addons/customer_outstanding_statement/views/statement.xml
odoo_addons/customer_outstanding_statement/wizard/__init__.py
odoo_addons/customer_outstanding_statement/wizard/customer_outstanding_statement_wizard.py
odoo_addons/customer_outstanding_statement/wizard/customer_outstanding_statement_wizard.xml
